proxyrequest/__init__.py
proxyrequest/utils.py
proxyrequest-0.17.dist-info/licenses/LICENSE
proxyrequest-0.17.dist-info/METADATA
proxyrequest-0.17.dist-info/WHEEL
proxyrequest-0.17.dist-info/top_level.txt
proxyrequest-0.17.dist-info/RECORD
