Metadata-Version: 2.4
Name: proxyrequest
Version: 0.17
Summary: A Python package for making HTTP requests with proxy support and fetching HTML content using requests or Selenium.
Author: Ramesh Chandra
Author-email: rameshsofter@gmail.com
Classifier: Programming Language :: Python :: 3
Classifier: License :: OSI Approved :: MIT License
Classifier: Operating System :: OS Independent
Requires-Python: >=3.6
License-File: LICENSE
Requires-Dist: fake-useragent
Requires-Dist: tldextract
Requires-Dist: selenium
Requires-Dist: requests
Requires-Dist: webdriver-manager
Requires-Dist: filetype
Requires-Dist: playwright
Dynamic: author
Dynamic: author-email
Dynamic: classifier
Dynamic: description
Dynamic: description-content-type
Dynamic: license-file
Dynamic: requires-dist
Dynamic: requires-python
Dynamic: summary
